Metadata-Version: 2.1
Name: GTNLib
Version: 0.2
Summary: Lib for project Guess The Number
Author: KeyDevS
Author-email: rumaevvadim@gmail.com
Classifier: Development Status :: 3 - Alpha
Classifier: Intended Audience :: Developers
Classifier: License :: OSI Approved :: MIT License
Classifier: Programming Language :: Python
